fold_to_ascii/__init__.py
fold_to_ascii/core.py
fold_to_ascii/mapping.py
tests/__init__.py
tests/context.py
tests/test_basic.py
tests/test_comprehensive.py
fold_to_ascii-1.0.2.dist-info/LICENSE
fold_to_ascii-1.0.2.dist-info/METADATA
fold_to_ascii-1.0.2.dist-info/WHEEL
fold_to_ascii-1.0.2.dist-info/top_level.txt
fold_to_ascii-1.0.2.dist-info/RECORD
