Metadata-Version: 2.1
Name: fold-to-ascii
Version: 1.0.2
Summary: A Python port of the Apache Lucene ASCII Folding Filter that converts alphabetic, numeric, and symbolic Unicode characters which are not in the first 127 ASCII characters (the ‘Basic Latin’ Unicode block) into ASCII equivalents, if they exist.
Home-page: https://github.com/spanishdict/fold_to_ascii
Author: William Bert
Author-email: william@spanishdict.com
License: MIT License
